ptf8/__init__.py
ptf8/asgi.py
ptf8/settings.py
ptf8/urls.py
ptf8/wsgi.py
ptf8-2.1.3.dist-info/LICENSE
ptf8-2.1.3.dist-info/METADATA
ptf8-2.1.3.dist-info/WHEEL
ptf8-2.1.3.dist-info/top_level.txt
ptf8-2.1.3.dist-info/RECORD
