Metadata-Version: 2.1
Name: ptf8
Version: 2.1.3
Summary: A package to run flake8 on pytest.
Home-page: https://github.com/pypa/sampleproject
Author: Daddy Finger
Author-email: author@example.com
License: UNKNOWN
Platform: UNKNOWN
Classifier: Programming Language :: Python :: 3
Classifier: License :: OSI Approved :: MIT License
Classifier: Operating System :: OS Independent
Requires-Python: >=3.6
